llm_together.py
llm_together-0.4.dist-info/LICENSE
llm_together-0.4.dist-info/METADATA
llm_together-0.4.dist-info/WHEEL
llm_together-0.4.dist-info/entry_points.txt
llm_together-0.4.dist-info/top_level.txt
llm_together-0.4.dist-info/RECORD
