Metadata-Version: 2.1
Name: llm-together
Version: 0.4
Summary: llm together plugin
Home-page: https://github.com/wearedevx/llm-together
Author: Kévin Quesada
License: MIT
Project-URL: Homepage, https://github.com/wearedevx/llm-together
Project-URL: Bug Tracker, https://github.com/wearedevx/llm-together/issues
Classifier: License :: OSI Approved :: Apache Software License
Requires-Python: >=3.7
License-File: LICENSE
Requires-Dist: llm >=0.5
Requires-Dist: together ==0.2.9
Provides-Extra: test
Requires-Dist: pytest ; extra == 'test'
